shiv/__init__.py
shiv/auto_model.py
shiv/metrics.py
ml_auto_trainer-0.1.0.dist-info/METADATA
ml_auto_trainer-0.1.0.dist-info/WHEEL
ml_auto_trainer-0.1.0.dist-info/top_level.txt
ml_auto_trainer-0.1.0.dist-info/RECORD
